<?xml version="1.0"?>
<metadata xml:lang="en"><Esri><CreaDate>20220107</CreaDate><CreaTime>16493600</CreaTime><ArcGISFormat>1.0</ArcGISFormat><SyncOnce>TRUE</SyncOnce><ModDate>20221219</ModDate><ModTime>193705</ModTime><scaleRange><minScale>150000000</minScale><maxScale>5000</maxScale></scaleRange><ArcGISProfile>ItemDescription</ArcGISProfile></Esri><toolbox name="WebInventoryToolboxForOutsideOfPro" alias="webtoolbox"><arcToolboxHelpPath>c:\program files\arcgis\pro\Resources\Help\gp</arcToolboxHelpPath><toolsets/></toolbox><dataIdInfo><idCitation><resTitle>WebInventoryToolboxForOutsideOfPro</resTitle></idCitation><idAbs>&lt;DIV STYLE="text-align:Left;"&gt;&lt;DIV&gt;&lt;DIV&gt;&lt;P&gt;&lt;SPAN&gt;Web Inventory Toolbox for ArcGIS Pro&lt;/SPAN&gt;&lt;/P&gt;&lt;/DIV&gt;&lt;/DIV&gt;&lt;/DIV&gt;</idAbs><idPurp>ArcGIS Pro tool to inventory Portal and/or ArcGIS Online services and/or web mapping applications in tabular format and/or user-friendly Excel spreadsheets.</idPurp><searchKeys><keyword>Portal; AGOL</keyword></searchKeys><idCredit>Arcadis N.A.</idCredit></dataIdInfo><distInfo><distributor><distorFormat><formatName>ArcToolbox Toolbox</formatName></distorFormat></distributor></distInfo><mdHrLv><ScopeCd value="005"/></mdHrLv><mdDateSt Sync="TRUE">20220726</mdDateSt></metadata>
